bluetooth/__init__.py
bluetooth/_msbt.cp310-win_amd64.pyd
bluetooth/ble.py
bluetooth/bluez.py
bluetooth/btcommon.py
bluetooth/macos.py
bluetooth/msbt.py
bluetooth/widcomm.py
PyBluez_bitalino-0.30.dist-info/COPYING
PyBluez_bitalino-0.30.dist-info/METADATA
PyBluez_bitalino-0.30.dist-info/WHEEL
PyBluez_bitalino-0.30.dist-info/eager_resources.txt
PyBluez_bitalino-0.30.dist-info/top_level.txt
PyBluez_bitalino-0.30.dist-info/zip-safe
PyBluez_bitalino-0.30.dist-info/RECORD
