Metadata-Version: 2.1
Name: PyBluez-bitalino
Version: 0.30
Summary: Bluetooth Python extension module
Home-page: UNKNOWN
Author: BitalinoWorld
Author-email: bitalino@plux.info
Maintainer: BitalinoWorld
License: GPL
Platform: UNKNOWN
Classifier: License :: OSI Approved :: GNU General Public License (GPL)
Classifier: Programming Language :: Python
Classifier: Programming Language :: Python :: 3
Classifier: Programming Language :: Python :: 3.7
Classifier: Programming Language :: Python :: 3.8
Classifier: Programming Language :: Python :: 3.9
Classifier: Programming Language :: Python :: 3.10
Classifier: Programming Language :: Python :: 3 :: Only
Classifier: Topic :: Communications
Requires-Python: >=3.7
Provides-Extra: ble
